{
  "ORDER_1775277534046": {
    "orderId": "ORDER_1775277534046",
    "amount": 19900,
    "description": "黄金会员",
    "paymentMethod": "wechat",
    "status": "pending",
    "createTime": "2026-04-04T04:38:56.128Z",
    "updateTime": "2026-04-04T04:38:56.129Z"
  },
  "ORDER_1775277546074": {
    "orderId": "ORDER_1775277546074",
    "amount": 39900,
    "description": "钻石会员",
    "paymentMethod": "wechat",
    "status": "pending",
    "createTime": "2026-04-04T04:39:09.158Z",
    "updateTime": "2026-04-04T04:39:09.158Z"
  },
  "ORDER_1775277562783": {
    "orderId": "ORDER_1775277562783",
    "amount": 59900,
    "description": "VIP会员",
    "paymentMethod": "wechat",
    "status": "pending",
    "createTime": "2026-04-04T04:39:26.292Z",
    "updateTime": "2026-04-04T04:39:26.292Z"
  },
  "ORDER_1775301099460": {
    "orderId": "ORDER_1775301099460",
    "amount": 19900,
    "description": "黄金会员",
    "paymentMethod": "wechat",
    "status": "pending",
    "createTime": "2026-04-04T11:11:44.371Z",
    "updateTime": "2026-04-04T11:11:44.372Z"
  },
  "ORDER_1775301131871": {
    "orderId": "ORDER_1775301131871",
    "amount": 19900,
    "description": "黄金会员",
    "paymentMethod": "wechat",
    "status": "pending",
    "createTime": "2026-04-04T11:12:13.666Z",
    "updateTime": "2026-04-04T11:12:13.666Z"
  },
  "ORDER_1775309516543": {
    "orderId": "ORDER_1775309516543",
    "amount": 19900,
    "description": "黄金会员",
    "paymentMethod": "wechat",
    "status": "pending",
    "createTime": "2026-04-04T13:32:02.602Z",
    "updateTime": "2026-04-04T13:32:02.603Z"
  }
}